s3_file_field_client/__init__.py
s3_file_field_client/py.typed
django_s3_file_field_client-1.1.0.dist-info/METADATA
django_s3_file_field_client-1.1.0.dist-info/WHEEL
django_s3_file_field_client-1.1.0.dist-info/RECORD
